README.md
pyproject.toml
setup.cfg
setup.py
diahook/__init__.py
diahook/api.py
diahook/receiver.py
diahook.egg-info/PKG-INFO
diahook.egg-info/SOURCES.txt
diahook.egg-info/dependency_links.txt
diahook.egg-info/requires.txt
diahook.egg-info/top_level.txt
diahook/openapi_client/__init__.py
diahook/openapi_client/api_client.py
diahook/openapi_client/configuration.py
diahook/openapi_client/exceptions.py
diahook/openapi_client/model_utils.py
diahook/openapi_client/rest.py
diahook/openapi_client/api/__init__.py
diahook/openapi_client/api/application_api.py
diahook/openapi_client/api/authentication_api.py
diahook/openapi_client/api/development_api.py
diahook/openapi_client/api/endpoint_api.py
diahook/openapi_client/api/event_type_api.py
diahook/openapi_client/api/health_api.py
diahook/openapi_client/api/message_api.py
diahook/openapi_client/api/message_attempt_api.py
diahook/openapi_client/apis/__init__.py
diahook/openapi_client/model/__init__.py
diahook/openapi_client/model/application_in.py
diahook/openapi_client/model/application_out.py
diahook/openapi_client/model/dashboard_access_out.py
diahook/openapi_client/model/endpoint_in.py
diahook/openapi_client/model/endpoint_message_out.py
diahook/openapi_client/model/endpoint_out.py
diahook/openapi_client/model/endpoint_secret.py
diahook/openapi_client/model/endpoint_stats.py
diahook/openapi_client/model/event_type_in_out.py
diahook/openapi_client/model/http_error_field.py
diahook/openapi_client/model/http_error_out.py
diahook/openapi_client/model/http_validation_error.py
diahook/openapi_client/model/list_response_application_out.py
diahook/openapi_client/model/list_response_endpoint_message_out.py
diahook/openapi_client/model/list_response_endpoint_out.py
diahook/openapi_client/model/list_response_event_type_in_out.py
diahook/openapi_client/model/list_response_message_attempt_endpoint_out.py
diahook/openapi_client/model/list_response_message_attempt_out.py
diahook/openapi_client/model/list_response_message_endpoint_out.py
diahook/openapi_client/model/list_response_message_out.py
diahook/openapi_client/model/message_attempt_endpoint_out.py
