Metadata-Version: 2.1
Name: diahook
Version: 0.8.6
Summary: Diahook
Home-page: https://www.diahook.com
Author: Diahook
Author-email: development@diahook.com
License: SEE LICENSE IN LICENSE.md
Keywords: diahook,webhooks
Platform: UNKNOWN
Requires-Python: >=3.6
